KIBIT/__init__.py
Kibit-0.0.2.dist-info/DESCRIPTION.rst
Kibit-0.0.2.dist-info/METADATA
Kibit-0.0.2.dist-info/RECORD
Kibit-0.0.2.dist-info/WHEEL
Kibit-0.0.2.dist-info/metadata.json
Kibit-0.0.2.dist-info/top_level.txt
