Metadata-Version: 2.0
Name: Kibit
Version: 0.0.2
Summary: Kibit Wrapper for python3
Home-page: http:/retty.me/
Author: Eshin Kunishima
Author-email: UNKNOWN
License: ASL
Platform: UNKNOWN
